{"id":"reference/troubleshooting","title":"Troubleshooting","url":"reference/troubleshooting.html","last_modified":"2026-04-07T21:07:17.878452+00:00","book":{"title":"NVIDIA NemoClaw Developer Guide","version":"latest"},"product":{"name":"NemoClaw","version":"latest"},"description":"Diagnose and resolve common NemoClaw installation, onboarding, and runtime issues.","description_agent":"Diagnoses and resolves common NemoClaw installation, onboarding, and runtime issues. Use when troubleshooting errors, debugging sandbox problems, or resolving setup failures.","tags":["openclaw","openshell","troubleshooting","nemoclaw"],"topics":["generative_ai","ai_agents"],"content_type":"reference","learning_level":"technical_beginner","audience":["developer","engineer"],"keywords":["nemoclaw troubleshooting","nemoclaw debug sandbox issues"],"content":"Troubleshooting This page covers common issues you may encounter when installing, onboarding, or running NemoClaw, along with their resolution steps. Get Help If your issue is not listed here, join the NemoClaw Discord channel to ask questions and get help from the community. You can also file an issue on GitHub . Installation nemoclaw not found after install If you use nvm or fnm to manage Node.js, the installer may not update your current shell’s PATH\nThe nemoclaw binary is installed but the shell session does not know where to find it. Run source ~/.bashrc (or source ~/.zshrc for zsh), or open a new terminal window. Installer fails on unsupported platform The installer checks for a supported OS and architecture before proceeding\nNemoClaw requires Linux Ubuntu 22.04 LTS or later\nIf you see an unsupported platform error, verify that you are running on a supported Linux distribution. Node.js version is too old NemoClaw requires Node.js 22.16 or later\nIf the installer exits with a Node.js version error, check your current version: $ node --version\nIf the version is below 22.16, install a supported release\nIf you use nvm, run: $ nvm install 22\nnvm use 22\nThen re-run the installer. Image push fails with out-of-memory errors The sandbox image is approximately 2.4 GB compressed. During image push, the Docker daemon, k3s, and the OpenShell gateway run alongside the export pipeline, which buffers decompressed layers in memory. On machines with less than 8 GB of RAM, this combined usage can trigger the OOM killer. If you cannot add memory, configure at least 8 GB of swap to work around the issue at the cost of slower performance. Docker is not running The installer and onboard wizard require Docker to be running\nIf you see a Docker connection error, start the Docker daemon: $ sudo systemctl start docker\nOn macOS with Docker Desktop, open the Docker Desktop application and wait for it to finish starting before retrying. macOS first-run failures The two most common first-run failures on macOS are missing developer tools and Docker connection errors. To avoid these issues, install the prerequisites in the following order before running the NemoClaw installer: Install Xcode Command Line Tools ( xcode-select --install ). These are needed by the installer and Node.js toolchain. Install and start a supported container runtime (Docker Desktop or Colima). Without a running runtime, the installer cannot connect to Docker. npm install fails with permission errors If npm install fails with an EACCES permission error, do not run npm with sudo\nInstead, configure npm to use a directory you own: $ mkdir -p ~/.npm-global\nnpm config set prefix ~/.npm-global\nexport PATH=~/.npm-global/bin:$PATH\nAdd the export line to your ~/.bashrc or ~/.zshrc to make it permanent, then re-run the installer. Port already in use The NemoClaw gateway uses port 18789 by default\nIf another process is already bound to this port, onboarding fails\nIdentify the conflicting process, verify it is safe to stop, and terminate it: $ sudo lsof -i :18789\nkill <PID\nIf the process does not exit, use kill -9 <PID> to force-terminate it\nThen retry onboarding. Onboarding Cgroup v2 errors during onboard Older NemoClaw releases relied on a Docker cgroup workaround on Ubuntu 24.04, DGX Spark, and WSL2\nCurrent OpenShell releases handle that behavior themselves, so NemoClaw no longer requires a Spark-specific setup step. If onboarding reports that Docker is missing or unreachable, fix Docker first and retry onboarding: $ nemoclaw onboard\nIf you are using Podman, NemoClaw warns and continues, but OpenShell officially documents Docker-based runtimes only\nIf onboarding or sandbox lifecycle fails, switch to Docker Desktop, Colima, or Docker Engine and rerun onboarding. Invalid sandbox name Sandbox names must follow RFC 1123 subdomain rules: lowercase alphanumeric characters and hyphens only, and must start and end with an alphanumeric character\nUppercase letters are automatically lowercased. If the name does not match these rules, the wizard exits with an error\nChoose a name such as my-assistant or dev1 . Sandbox creation fails on DGX On DGX machines, sandbox creation can fail if the gateway’s DNS has not finished propagating or if a stale port forward from a previous onboard run is still active. Run nemoclaw onboard to retry\nThe wizard cleans up stale port forwards and waits for gateway readiness automatically. Colima socket not detected (macOS) Newer Colima versions use the XDG base directory ( ~/.config/colima/default/docker.sock ) instead of the legacy path ( ~/.colima/default/docker.sock\nNemoClaw checks both paths\nIf neither is found, verify that Colima is running: $ colima status\nSandbox creation killed by OOM (exit 137) On systems with 8 GB RAM or less and no swap configured, the sandbox image push can exhaust available memory and get killed by the Linux OOM killer (exit code 137). NemoClaw automatically detects low memory during onboarding and prompts to create a 4 GB swap file\nIf this automatic step fails or you are using a custom setup flow, create swap manually before running nemoclaw onboard : $ sudo dd if=/dev/zero of=/swapfile bs=1M count=4096 status=none\nsudo chmod 600 /swapfile\nsudo mkswap /swapfile\nsudo swapon /swapfile\necho '/swapfile none swap sw 0 0' | sudo tee -a /etc/fstab\nnemoclaw onboard\nRuntime Reconnect after a host reboot After a host reboot, the container runtime, OpenShell gateway, and sandbox may not be running\nFollow these steps to reconnect. Start the container runtime. Linux: start Docker if it is not already running ( sudo systemctl start docker ) macOS: open Docker Desktop or start Colima ( colima start ) Check sandbox state. $ openshell sandbox list\nIf the sandbox shows Ready , skip to step 4. Restart the gateway (if needed). If the sandbox is not listed or the command fails, restart the OpenShell gateway: $ openshell gateway start --name nemoclaw\nWait a few seconds, then re-check with openshell sandbox list . Reconnect. $ nemoclaw <name> connect\nStart auxiliary services (if needed). If you use the Telegram bridge or cloudflared tunnel, start them again: $ nemoclaw start\nIf the sandbox does not recover If the sandbox remains missing after restarting the gateway, run nemoclaw onboard to recreate it\nThe wizard prompts for confirmation before destroying an existing sandbox. If you confirm, it destroys and recreates the sandbox — workspace files (SOUL.md, USER.md, IDENTITY.md, AGENTS.md, MEMORY.md, and daily memory notes) are lost\nBack up your workspace first by following the instructions at Back Up and Restore . Sandbox shows as stopped The sandbox may have been stopped or deleted\nRun nemoclaw onboard to recreate the sandbox from the same blueprint and policy definitions. Status shows “not running” inside the sandbox This is expected behavior\nWhen checking status inside an active sandbox, host-side sandbox state and inference configuration are not inspectable\nThe status command detects the sandbox context and reports “active (inside sandbox)” instead. Run openshell sandbox list on the host to check the underlying sandbox state. Inference requests time out Verify that the inference provider endpoint is reachable from the host\nCheck the active provider and endpoint: $ nemoclaw <name> status\nIf the endpoint is correct but requests still fail, check for network policy rules that may block the connection\nThen verify the credential and base URL for the provider you selected during onboarding. Agent cannot reach an external host OpenShell blocks outbound connections to hosts not listed in the network policy\nOpen the TUI to see blocked requests and approve them: $ openshell term\nTo permanently allow an endpoint, add it to the network policy\nRefer to Customize the Network Policy for details. Blueprint run failed View the error output for the failed blueprint run: $ nemoclaw <name> logs\nUse --follow to stream logs in real time while debugging","format":"text","summary":"This page covers common issues you may encounter when installing, onboarding, or running NemoClaw, along with their resolution steps.","headings":[{"text":"Troubleshooting","level":1},{"text":"Installation","level":2},{"text":"nemoclaw not found after install","level":3},{"text":"Installer fails on unsupported platform","level":3},{"text":"Node.js version is too old","level":3},{"text":"Image push fails with out-of-memory errors","level":3},{"text":"Docker is not running","level":3},{"text":"macOS first-run failures","level":3},{"text":"npm install fails with permission errors","level":3},{"text":"Port already in use","level":3},{"text":"Onboarding","level":2},{"text":"Cgroup v2 errors during onboard","level":3},{"text":"Invalid sandbox name","level":3},{"text":"Sandbox creation fails on DGX","level":3},{"text":"Colima socket not detected (macOS)","level":3},{"text":"Sandbox creation killed by OOM (exit 137)","level":3},{"text":"Runtime","level":2},{"text":"Reconnect after a host reboot","level":3},{"text":"Sandbox shows as stopped","level":3},{"text":"Status shows “not running” inside the sandbox","level":3},{"text":"Inference requests time out","level":3},{"text":"Agent cannot reach an external host","level":3},{"text":"Blueprint run failed","level":3},{"text":"Get Help","level":1},{"text":"If the sandbox does not recover","level":1}]}